phone_number_validator445566/__init__.py
phone_number_validator445566/desktop.ini
phone_number_validator445566/main.py
phone_number_validator445566/validator.py
phone_number_validator445566-0.2.0.dist-info/METADATA
phone_number_validator445566-0.2.0.dist-info/WHEEL
phone_number_validator445566-0.2.0.dist-info/RECORD
