Metadata-Version: 2.1
Name: phone-number-validator445566
Version: 0.2.0
Summary: 
Author: Your Name
Author-email: you@example.com
Requires-Python: >=3.11,<4.0
Classifier: Programming Language :: Python :: 3
Classifier: Programming Language :: Python :: 3.11
Requires-Dist: requests (>=2.31.0,<3.0.0)
